pytest_tspwplib.py
pytest_tspwplib-0.2.6.dist-info/LICENSE
pytest_tspwplib-0.2.6.dist-info/METADATA
pytest_tspwplib-0.2.6.dist-info/WHEEL
pytest_tspwplib-0.2.6.dist-info/entry_points.txt
pytest_tspwplib-0.2.6.dist-info/top_level.txt
pytest_tspwplib-0.2.6.dist-info/RECORD
