Metadata-Version: 2.1
Name: pytest-tspwplib
Version: 0.2.6
Summary: A simple plugin to use with tspwplib
Home-page: https://github.com/PatrickOHara/pytest-tspwplib
Author: Patrick O'Hara
Author-email: pohara@turing.ac.uk
Maintainer: Patrick O'Hara
Maintainer-email: pohara@turing.ac.uk
License: MIT
Platform: UNKNOWN
Classifier: Development Status :: 4 - Beta
Classifier: Framework :: Pytest
Classifier: Intended Audience :: Developers
Classifier: Topic :: Software Development :: Testing
Classifier: Programming Language :: Python
Classifier: Programming Language :: Python :: 3
Classifier: Programming Language :: Python :: 3.6
Classifier: Programming Language :: Python :: 3.7
Classifier: Programming Language :: Python :: 3.8
Classifier: Programming Language :: Python :: 3 :: Only
Classifier: Programming Language :: Python :: Implementation :: CPython
Classifier: Programming Language :: Python :: Implementation :: PyPy
Classifier: Operating System :: OS Independent
Classifier: License :: OSI Approved :: MIT License
Requires-Python: >=3.6
Requires-Dist: tspwplib (>=0.4.1)
Requires-Dist: pytest (>=3.5.0)
